waggylabs/__init__.py
waggylabs/admin.py
waggylabs/apps.py
waggylabs/forms.py
waggylabs/middleware.py
waggylabs/panels.py
waggylabs/snippets.py
waggylabs/tests.py
waggylabs/urls.py
waggylabs/utils.py
waggylabs/views.py
waggylabs/wagtail_hooks.py
waggylabs/admin/__init__.py
waggylabs/admin/panels.py
waggylabs/blocks/__init__.py
waggylabs/blocks/accordion.py
waggylabs/blocks/base_body.py
waggylabs/blocks/blockquote.py
waggylabs/blocks/card_grid.py
waggylabs/blocks/carousel.py
waggylabs/blocks/citation.py
waggylabs/blocks/code.py
waggylabs/blocks/collapse.py
waggylabs/blocks/columns.py
waggylabs/blocks/cut.py
waggylabs/blocks/document.py
waggylabs/blocks/embed.py
waggylabs/blocks/equation.py
waggylabs/blocks/figure.py
waggylabs/blocks/footer_menu.py
waggylabs/blocks/icon.py
waggylabs/blocks/label.py
waggylabs/blocks/link_list.py
waggylabs/blocks/links.py
waggylabs/blocks/listing.py
waggylabs/blocks/markdown.py
waggylabs/blocks/math.py
waggylabs/blocks/page_info.py
waggylabs/blocks/post_archive.py
waggylabs/blocks/post_body.py
waggylabs/blocks/post_category_list.py
waggylabs/blocks/post_highlights.py
waggylabs/blocks/post_list.py
waggylabs/blocks/post_list_body.py
waggylabs/blocks/post_meta.py
waggylabs/blocks/post_series.py
waggylabs/blocks/post_tag_list.py
waggylabs/blocks/sidebar.py
waggylabs/blocks/sidebar_items.py
waggylabs/blocks/sidebar_tabs.py
waggylabs/blocks/styling.py
waggylabs/blocks/table.py
waggylabs/blocks/visuals.py
waggylabs/blocks/wrapper.py
waggylabs/extensions/__init__.py
waggylabs/extensions/markdown.py
waggylabs/fields/0003_hitcount.py
waggylabs/fields/__init__.py
waggylabs/fields/markdown.py
waggylabs/management/__init__.py
waggylabs/management/commands/__init__.py
waggylabs/management/commands/createsuperuser_container.py
waggylabs/management/commands/makemigrations.py
waggylabs/migrations/0001_initial.py
waggylabs/migrations/0002_create_sitepage.py
waggylabs/migrations/0003_alter_waggylabssettings_navbar_active_link_color_and_more.py
wagtail_waggylabs-1.1.2.dist-info/LICENSE
wagtail_waggylabs-1.1.2.dist-info/METADATA
wagtail_waggylabs-1.1.2.dist-info/WHEEL
wagtail_waggylabs-1.1.2.dist-info/top_level.txt
wagtail_waggylabs-1.1.2.dist-info/RECORD
