Metadata-Version: 2.1
Name: wagtail-waggylabs
Version: 1.1.2
Summary: A Wagtail app for research group and scientific blog sites.
Author-email: Konstantin Tamarov <ktamarov@gmail.com>
Maintainer-email: Konstantin Tamarov <ktamarov@gmail.com>
License: The MIT License (MIT)
Project-URL: Homepage, https://ktamarov.com/demo-page
Project-URL: Bug Reports, https://github.com/natisok/wagtail-waggylabs/issues
Project-URL: Source, https://github.com/natisok/wagtail-waggylabs/
Keywords: Wagtail,Research,Blog
Classifier: Development Status :: 4 - Beta
Classifier: Environment :: Web Environment
Classifier: Framework :: Django
Classifier: Framework :: Django :: 5.0
Classifier: Framework :: Wagtail
Classifier: Framework :: Wagtail :: 6
Classifier: Intended Audience :: Developers
Classifier: Intended Audience :: Science/Research
Classifier: License :: OSI Approved :: MIT License
Classifier: Operating System :: OS Independent
Classifier: Programming Language :: Python
Classifier: Programming Language :: Python :: 3
Classifier: Programming Language :: Python :: 3 :: Only
Classifier: Programming Language :: Python :: 3.11
Classifier: Topic :: Internet :: WWW/HTTP
Classifier: Topic :: Internet :: WWW/HTTP :: Dynamic Content
Requires-Python: >=3.10
License-File: LICENSE
Requires-Dist: Django <5.1,>=5.0
Requires-Dist: django-el-pagination >=4.0.0
Requires-Dist: django-taggit <5.1,>=5.0
Requires-Dist: django-hitcount >=1.3.5
Requires-Dist: django-simple-captcha >=0.6.0
Requires-Dist: emoji >=2.12.1
Requires-Dist: psycopg2 >=2.9.9
Requires-Dist: pygments >=2.18.0
Requires-Dist: wagtail >=6.2.1
Requires-Dist: wagtail-markdown >=0.12.1
Requires-Dist: wagtailmenus >=4.0.1
Requires-Dist: wagtail-metadata >=5.0.0
